mtrand
