Metadata-Version: 1.0
Name: mtrand
Version: 0.1
Summary: Mersenne Twister PRNG for Numeric
Home-page: http://starship.python.net/crew/kernr/source/
Author: Robert Kern
Author-email: robert.kern@gmail.com
License: MIT
Download-URL: http://starship.python.net/crew/kernr/source/
Platform: UNKNOWN
Classifier: Development Status :: 4 - Beta
Classifier: Intended Audience :: Developers
Classifier: Intended Audience :: Science/Research
Classifier: License :: OSI Approved :: MIT License
Classifier: Operating System :: MacOS :: MacOS X
Classifier: Operating System :: Microsoft :: Windows
Classifier: Operating System :: POSIX
Classifier: Programming Language :: Python
Classifier: Programming Language :: C
Classifier: Topic :: Scientific/Engineering
Classifier: Topic :: Software Development :: Libraries :: Python Modules
